mkdocstrings_handlers/python/__init__.py
mkdocstrings_handlers/python/_internal/__init__.py
mkdocstrings_handlers/python/_internal/config.py
mkdocstrings_handlers/python/_internal/debug.py
mkdocstrings_handlers/python/_internal/handler.py
mkdocstrings_handlers/python/_internal/rendering.py
mkdocstrings_handlers/python/config.py
mkdocstrings_handlers/python/handler.py
mkdocstrings_handlers/python/py.typed
mkdocstrings_handlers/python/rendering.py
mkdocstrings_handlers/python/templates/material/_base/attribute.html
mkdocstrings_handlers/python/templates/material/_base/attribute.html.jinja
mkdocstrings_handlers/python/templates/material/_base/backlinks.html.jinja
mkdocstrings_handlers/python/templates/material/_base/children.html
mkdocstrings_handlers/python/templates/material/_base/children.html.jinja
mkdocstrings_handlers/python/templates/material/_base/class.html
mkdocstrings_handlers/python/templates/material/_base/class.html.jinja
mkdocstrings_handlers/python/templates/material/_base/docstring.html
mkdocstrings_handlers/python/templates/material/_base/docstring.html.jinja
mkdocstrings_handlers/python/templates/material/_base/docstring/admonition.html
mkdocstrings_handlers/python/templates/material/_base/docstring/admonition.html.jinja
mkdocstrings_handlers/python/templates/material/_base/docstring/attributes.html
mkdocstrings_handlers/python/templates/material/_base/docstring/attributes.html.jinja
mkdocstrings_handlers/python/templates/material/_base/docstring/classes.html
mkdocstrings_handlers/python/templates/material/_base/docstring/classes.html.jinja
mkdocstrings_handlers/python/templates/material/_base/docstring/examples.html
mkdocstrings_handlers/python/templates/material/_base/docstring/examples.html.jinja
mkdocstrings_handlers/python/templates/material/_base/docstring/functions.html
mkdocstrings_handlers/python/templates/material/_base/docstring/functions.html.jinja
mkdocstrings_handlers/python/templates/material/_base/docstring/modules.html
mkdocstrings_python-1.18.1.dist-info/METADATA
mkdocstrings_python-1.18.1.dist-info/WHEEL
mkdocstrings_python-1.18.1.dist-info/entry_points.txt
mkdocstrings_python-1.18.1.dist-info/licenses/LICENSE
mkdocstrings_python-1.18.1.dist-info/RECORD
