Metadata-Version: 2.4
Name: mkdocstrings-python
Version: 1.18.1
Summary: A Python handler for mkdocstrings.
Author-Email: =?utf-8?q?Timoth=C3=A9e_Mazzucotelli?= <dev@pawamoy.fr>
License-Expression: ISC
License-File: LICENSE
Classifier: Development Status :: 4 - Beta
Classifier: Intended Audience :: Developers
Classifier: Programming Language :: Python
Classifier: Programming Language :: Python :: 3
Classifier: Programming Language :: Python :: 3 :: Only
Classifier: Programming Language :: Python :: 3.9
Classifier: Programming Language :: Python :: 3.10
Classifier: Programming Language :: Python :: 3.11
Classifier: Programming Language :: Python :: 3.12
Classifier: Programming Language :: Python :: 3.13
Classifier: Programming Language :: Python :: 3.14
Classifier: Topic :: Documentation
Classifier: Topic :: Software Development
Classifier: Topic :: Software Development :: Documentation
Classifier: Topic :: Utilities
Classifier: Typing :: Typed
Project-URL: Homepage, https://mkdocstrings.github.io/python
Project-URL: Documentation, https://mkdocstrings.github.io/python
Project-URL: Changelog, https://mkdocstrings.github.io/python/changelog
Project-URL: Repository, https://github.com/mkdocstrings/python
Project-URL: Issues, https://github.com/mkdocstrings/python/issues
Project-URL: Discussions, https://github.com/mkdocstrings/python/discussions
Project-URL: Gitter, https://gitter.im/mkdocstrings/python
Project-URL: Funding, https://github.com/sponsors/pawamoy
Requires-Python: >=3.9
Requires-Dist: mkdocstrings>=0.30
Requires-Dist: mkdocs-autorefs>=1.4
Requires-Dist: griffe>=1.13
Requires-Dist: typing-extensions>=4.0; python_version < "3.11"
